volcano/mbsrv/__init__.py
volcano/mbsrv/__main__.py
volcano/mbsrv/device.py
volcano/mbsrv/mb_rules.py
volcano/mbsrv/mb_server.py
volcano/mbsrv/mb_srv_protocol.py
volcano_mbsrv-1.1.14.dist-info/LICENSE
volcano_mbsrv-1.1.14.dist-info/METADATA
volcano_mbsrv-1.1.14.dist-info/WHEEL
volcano_mbsrv-1.1.14.dist-info/top_level.txt
volcano_mbsrv-1.1.14.dist-info/RECORD
