Metadata-Version: 2.1
Name: volcano-mbsrv
Version: 1.1.14
Summary: Modbus server satellite for Volcano
Home-page: UNKNOWN
Author: Vinogradov D
Author-email: dgrapes@gmail.com
License: MIT
Platform: UNKNOWN
Requires-Dist: volcano-general
Requires-Dist: volcano-twistedclient
Requires-Dist: twisted
